classification_model/VERSION
classification_model/__init__.py
classification_model/config.yml
classification_model/pipeline.py
classification_model/predict.py
classification_model/train_pipeline.py
classification_model/config/__init__.py
classification_model/config/core.py
classification_model/datasets/__init__.py
classification_model/datasets/raw.csv
classification_model/processing/__init__.py
classification_model/processing/data_manager.py
classification_model/processing/features.py
classification_model/processing/validation.py
classification_model/trained_models/__init__.py
classification_model/trained_models/titanic_classification_model_output_v0.0.6.pkl
manrodri_test_titanic_classification_model-0.0.6.dist-info/METADATA
manrodri_test_titanic_classification_model-0.0.6.dist-info/WHEEL
manrodri_test_titanic_classification_model-0.0.6.dist-info/top_level.txt
manrodri_test_titanic_classification_model-0.0.6.dist-info/RECORD
